README.rst
setup.py
tkCanvasGraph/__init__.py
tkCanvasGraph/__main__.py
tkCanvasGraph/canvas.py
tkCanvasGraph/exception.py
tkCanvasGraph/graph.py
tkCanvasGraph/layout.py
tkCanvasGraph/mouse.py
tkCanvasGraph/shape.py
tkCanvasGraph/util.py
tkCanvasGraph.egg-info/PKG-INFO
tkCanvasGraph.egg-info/SOURCES.txt
tkCanvasGraph.egg-info/dependency_links.txt
tkCanvasGraph.egg-info/top_level.txt