Metadata-Version: 1.1
Name: tkCanvasGraph
Version: 1.0
Summary: A library to display and manipulate graphs on a tkinter canvas.
Home-page: https://github.com/sbusard/tkCanvasGraph
Author: Simon Busard
Author-email: simon.busard@gmail.com
License: MIT
Keywords: graph visualisation
Platform: UNKNOWN
Classifier: Intended Audience :: Developers
Classifier: Topic :: Utilities
Classifier: License :: OSI Approved :: MIT License
Classifier: Programming Language :: Python :: 3
